sathouel_ftp_client/__init__.py
sathouel_ftp_client/client.py
sathouel_ftp_client-0.1.0.dist-info/WHEEL
sathouel_ftp_client-0.1.0.dist-info/METADATA
sathouel_ftp_client-0.1.0.dist-info/RECORD
