Metadata-Version: 2.1
Name: sathouel-ftp-client
Version: 0.1.0
Summary: 
Author: Steven Athouel
Author-email: sathouel@gmail.com
Requires-Python: >=3.9,<4.0
Classifier: Programming Language :: Python :: 3
Classifier: Programming Language :: Python :: 3.9
Classifier: Programming Language :: Python :: 3.10
Classifier: Programming Language :: Python :: 3.11
Requires-Dist: paramiko (>=3.2.0,<4.0.0)
